bq_estimator.py
bq_estimator-1.0.1.dist-info/LICENSE
bq_estimator-1.0.1.dist-info/METADATA
bq_estimator-1.0.1.dist-info/WHEEL
bq_estimator-1.0.1.dist-info/entry_points.txt
bq_estimator-1.0.1.dist-info/top_level.txt
bq_estimator-1.0.1.dist-info/RECORD
