Metadata-Version: 2.1
Name: bq-estimator
Version: 1.0.1
Summary: estimate BigQuery usage of sql queries
Home-page: https://github.com/j-clemons/bq-estimator
Author: Jonathan Clemons
Author-email: j-clemons@tuta.io
License: MIT
Classifier: License :: OSI Approved :: MIT License
Classifier: Programming Language :: Python :: 3
Classifier: Programming Language :: Python :: 3 :: Only
Requires-Python: >=3.8
License-File: LICENSE
Requires-Dist: dbt-core (>=1.5.0)
Requires-Dist: google-cloud-bigquery (>=3.7.0)
